treegear/__init__.py
treegear-0.0.0.7.dist-info/LICENSE
treegear-0.0.0.7.dist-info/METADATA
treegear-0.0.0.7.dist-info/WHEEL
treegear-0.0.0.7.dist-info/top_level.txt
treegear-0.0.0.7.dist-info/RECORD
