Metadata-Version: 2.1
Name: treegear
Version: 0.0.0.7
Summary: This module is for tests for future project.
Home-page: http://treegear.dev
Author: Gyuli
Author-email: treegear.dev@gmail.com
Project-URL: Documentation, http://treegear.dev
Keywords: python uvicorn
Classifier: Programming Language :: Python :: 3.11
Classifier: License :: OSI Approved :: MIT License
Classifier: Operating System :: OS Independent
Requires-Python: >=3.8
License-File: LICENSE
Requires-Dist: click==8.1.7
Requires-Dist: h11==0.14.0
Requires-Dist: uvicorn==0.30.6
